letsdebughelper/__init__.py
letsdebughelper/helpers.py
letsdebughelper/letsdebug.py
letsdebughelper/tests/__init__.py
letsdebughelper/tests/test_helpers.py
letsdebughelper/tests/test_letsdebug.py
lets_debug_helper-1.5.22.dist-info/METADATA
lets_debug_helper-1.5.22.dist-info/WHEEL
lets_debug_helper-1.5.22.dist-info/entry_points.txt
lets_debug_helper-1.5.22.dist-info/licenses/LICENSE
lets_debug_helper-1.5.22.dist-info/RECORD
