Metadata-Version: 2.4
Name: lets-debug-helper
Version: 1.5.22
Summary: This is a cli tool that interacts with the Let's Debug API
License: License :: OSI Approved :: MIT License
License-File: LICENSE
Author: Jeffrey Crane
Author-email: jediknight11206@gmail.com
Requires-Python: >=3.9,<4.0
Classifier: License :: Other/Proprietary License
Classifier: Programming Language :: Python :: 3
Classifier: Programming Language :: Python :: 3.9
Classifier: Programming Language :: Python :: 3.10
Classifier: Programming Language :: Python :: 3.11
Classifier: Programming Language :: Python :: 3.12
Classifier: Programming Language :: Python :: 3.13
Classifier: Programming Language :: Python :: 3.14
Requires-Dist: argparse (>=1.4.0,<2.0.0)
Requires-Dist: requests (>=2.31.0,<3.0.0)
Requires-Dist: rich (>=13.7.0,<14.0.0)
Requires-Dist: six (>=1.16.0,<2.0.0)
